dwaoAdobeIO/AdobeAuth.py
dwaoAdobeIO/__init.py
dwaoAdobeIO-0.1.3.1.dist-info/LICENSE
dwaoAdobeIO-0.1.3.1.dist-info/METADATA
dwaoAdobeIO-0.1.3.1.dist-info/WHEEL
dwaoAdobeIO-0.1.3.1.dist-info/top_level.txt
dwaoAdobeIO-0.1.3.1.dist-info/RECORD
